pyfilm/__init__.py
pyfilm/pyfilm.py
pyfilm-0.3.0.dist-info/LICENSE.txt
pyfilm-0.3.0.dist-info/METADATA
pyfilm-0.3.0.dist-info/WHEEL
pyfilm-0.3.0.dist-info/top_level.txt
pyfilm-0.3.0.dist-info/RECORD
