Metadata-Version: 2.1
Name: pyfilm
Version: 0.3.0
Summary: Easily create 1D and 2D films of NumPy arrays.
Home-page: https://github.com/ferdinandvwyk/pyfilm.git
Author: Ferdinand van Wyk
Author-email: ferdinandvwyk@gmail.com
License: GNU
Keywords: film,video,animation,numpy,ffmpeg,avconv
Platform: UNKNOWN
Classifier: Development Status :: 3 - Alpha
Classifier: Programming Language :: Python
Classifier: Programming Language :: Python :: 3
Classifier: Programming Language :: Python :: 3.6
Classifier: Programming Language :: Python :: 3.7
Classifier: Programming Language :: Python :: 3.8
Classifier: Programming Language :: Python :: 3.9
Classifier: Operating System :: MacOS
Classifier: Operating System :: POSIX
Classifier: Operating System :: Unix
Classifier: Intended Audience :: Developers
Classifier: Intended Audience :: Science/Research
Classifier: Topic :: Multimedia :: Video
Requires-Dist: matplotlib (>1.4)
Requires-Dist: py-cpuinfo (>0.1)
Requires-Dist: Pillow (>2.8)
